nwisepy/IPO.py
nwisepy/__init__.py
nwisepy-1.0.1.dist-info/METADATA
nwisepy-1.0.1.dist-info/WHEEL
nwisepy-1.0.1.dist-info/licenses/LICENSE
nwisepy-1.0.1.dist-info/RECORD
