Metadata-Version: 2.1
Name: nwisepy
Version: 1.0.1
Summary: A simple tool to generate pairwise testing set
Project-URL: Homepage, https://github.com/Oliver-242/ipo
Author-email: Oliver Cai <cjz210oliver@gmail.com>
License-File: LICENSE
Classifier: License :: OSI Approved :: MIT License
Classifier: Operating System :: OS Independent
Classifier: Programming Language :: Python :: 3
Requires-Python: >=3.8
